Workbook

Sheet Raw_Data
A1: INVOICE_ID | B1: Customer_name | C1: Sector | D1: Invoice_Data | E1: Due_Data | F1: Paid_Data | G1: Invoice_Amount | H1: COGS | I1: Gross_Profit | J1: Payment_Status
A2: INV-101 | B2: Alpha Corp | C2: Technology | D2: 45296 | E2: 45326 | F2: 45324 | G2: 15000 | H2: 9000 | I2: =G2-H2 -> 6000 | J2: =IF(F2="","UNPAID","PAID") -> PAID
A3: INV-102 | B3: Beta Retail | C3: Retail | D3: 45301 | E3: 45331 | F3: 45352 | G3: 8500 | H3: 5500 | I3: =G3-H3 -> 3000 | J3: =IF(F3="","UNPAID","PAID") -> PAID
A4: INV-103 | B4: Gamma Build | C4: Manufacturing | D4: 45306 | E4: 45336 | G4: 22000 | H4: 14000 | I4: =G4-H4 -> 8000 | J4: =IF(F4="","UNPAID","PAID") -> UNPAID
A5: INV-104 | B5: Delta Tech | C5: Technology | D5: 45323 | E5: 45353 | F5: 45352 | G5: 12000 | H5: 7000 | I5: =G5-H5 -> 5000 | J5: =IF(F5="","UNPAID","PAID") -> PAID
A6: INV-105 | B6: Epsilon Store | C6: Retail | D6: 45332 | E6: 45362 | G6: 6400 | H6: 4100 | I6: =G6-H6 -> 2300 | J6: =IF(F6="","UNPAID","PAID") -> UNPAID
A7: INV-106 | B7: Zeta Factory | C7: Manufacturing | D7: 45337 | E7: 45367 | F7: 45392 | G7: 31000 | H7: 20000 | I7: =G7-H7 -> 11000 | J7: =IF(F7="","UNPAID","PAID") -> PAID
A8: INV-107 | B8: Theta Apps | C8: Technology | D8: 45352 | E8: 45382 | G8: 18500 | H8: 10500 | I8: =G8-H8 -> 8000 | J8: =IF(F8="","UNPAID","PAID") -> UNPAID
A9: INV-108 | B9: Omega Mart | C9: Retail | D9: 45356 | E9: 45386 | G9: 9200 | H9: 6000 | I9: =G9-H9 -> 3200 | J9: =IF(F9="","UNPAID","PAID") -> UNPAID

Sheet Calculations
A1: Metric | B1: Value | D1: Sector | E1: Revenue
A2: Total revenue | B2: 122600 | D2: Technology | E2: =SUMIF(Raw_Data!C:C, D2, Raw_Data!G:G) -> 45500
A3: Total COGS | B3: 76100 | D3: Retail | E3: =SUMIF(Raw_Data!C:C, D3, Raw_Data!G:G) -> 24100
A4: Total Gross Profit | B4: 46500 | D4: Manufacturing | E4: =SUMIF(Raw_Data!C:C, D4, Raw_Data!G:G) -> 53000
A5: Gross Profit margin % | B5: =B4/B2 -> 0.37928222

Sheet Dashboard
B2: Corporate Profitability & Working Capital Dashboard
B4: Total Revenue | D4: Gross Profit Margin
B5: =Calculations!B2 -> 122600 | D5: =Calculations!B5 -> 0.37928222
